{
	"AOM": {
		"href": "https://wicg.github.io/aom/spec/",
		"title": "Accessibility Object Model"
	},
	"BACKGROUND-FETCH": {
		"href": "https://wicg.github.io/background-fetch/",
		"title": "Background Fetch"
	},
	"BADGING": {
		"href": "https://wicg.github.io/badging/",
		"title": "Badging API"
	},
	"BUDGET-API": {
		"href": "https://wicg.github.io/budget-api/",
		"title": "Web Budget API"
	},
	"COOKIE-STORE": {
		"href": "https://wicg.github.io/cookie-store/",
		"title": "Cookie Store API"
	},
	"CORS-RFC1918": {
		"href": "https://wicg.github.io/cors-rfc1918/",
		"title": "CORS and RFC1918"
	},
	"ELEMENT-TIMING": {
		"href": "https://wicg.github.io/element-timing/",
		"title": "Element Timing API"
	},
	"ENTRIES-API": {
		"href": "https://wicg.github.io/entries-api/",
		"title": "File and Directory Entries API"
	},
	"EVENT-TIMING": {
		"href": "https://wicg.github.io/event-timing/",
		"title": "Event Timing API"
	},
	"FRAME-TIMING": {
		"href": "https://wicg.github.io/frame-timing/",
		"title": "Frame Timing"
	},
	"INPUT-DEVICE-CAPABILITIES": {
		"href": "https://wicg.github.io/InputDeviceCapabilities/",
		"title": "Input Device Capabilities"
	},
	"JS-SELF-PROFILING": {
		"href": "https://wicg.github.io/js-self-profiling/",
		"title": "JS Self-Profiling API"
	},
	"KEYBOARD-LOCK": {
		"href": "https://wicg.github.io/keyboard-lock/",
		"title": "Keyboard Lock"
	},
	"KEYBOARD-MAP": {
		"href": "https://wicg.github.io/keyboard-map/",
		"title": "Keyboard Map"
	},
	"KV-STORAGE": {
		"href": "https://wicg.github.io/kv-storage/",
		"title": "KV Storage"
	},
	"LAYOUT-INSTABILITY": {
		"href": "https://wicg.github.io/layout-instability/",
		"title": "Layout Instability"
	},
	"LARGEST-CONTENTFUL-PAINT": {
		"href": "https://wicg.github.io/largest-contentful-paint/",
		"title": "Largest Contentful Paint"
	},
	"NATIVE-FILE-SYSTEM": {
		"href": "https://wicg.github.io/native-file-system/",
		"title": "Native File System"
	},
	"NETINFO": {
		"href": "https://wicg.github.io/netinfo/",
		"title": "Network Information API"
	},
	"ORIGIN-POLICY": {
		"href": "https://wicg.github.io/origin-policy/",
		"title": "Origin Policy"
	},
	"PAGE-LIFECYCLE": {
		"href": "https://wicg.github.io/page-lifecycle/",
		"title": "Page Lifecycle"
	},
	"PERMISSIONS-REQUEST": {
		"href": "https://wicg.github.io/permissions-request/",
		"title": "Requesting Permissions"
	},
	"PERMISSIONS-REVOKE": {
		"href": "https://wicg.github.io/permissions-revoke/",
		"title": "Relinquishing Permissions"
	},
	"PRIORITY-HINTS": {
		"href": "https://wicg.github.io/priority-hints/",
		"title": "Priority Hints"
	},
	"SCROLL-ANIMATIONS": {
		"href": "https://wicg.github.io/scroll-animations/",
		"title": "Scroll-linked Animations"
	},
	"SHAPE-DETECTION-API": {
		"href": "https://wicg.github.io/shape-detection-api/",
		"title": "Accelerated Shape Detection in Images"
	},
	"SMS-ONE-TIME-CODES": {
		"href": "https://wicg.github.io/sms-one-time-codes/",
		"title": "Origin-bound one-time codes delivered via SMS"
	},
	"SPEECH-API": {
		"href": "https://wicg.github.io/speech-api/",
		"title": "Web Speech API"
	},
	"TEXT-DETECTION-API": {
		"href": "https://wicg.github.io/shape-detection-api/text.html",
		"title": "Accelerated Text Detection in Images"
	},
	"TRUSTED-TYPES": {
		"href": "https://wicg.github.io/trusted-types/dist/spec/",
		"title": "Trusted Types Spec WIP"
	},
	"VISUAL-VIEWPORT": {
		"href": "https://wicg.github.io/visual-viewport/",
		"title": "Visual Viewport API"
	},
	"WEB-BACKGROUND-SYNC": {
		"href": "https://wicg.github.io/BackgroundSync/spec/",
		"title": "Web Background Synchronization"
	},
	"PERIODIC-BACKGROUND-SYNC": {
		"href": "https://wicg.github.io/BackgroundSync/spec/PeriodicBackgroundSync-index.html",
		"title": "Web Periodic Background Synchronization"
	},
	"WEB-LOCKS": {
		"href": "https://wicg.github.io/web-locks/",
		"title": "Web Locks API"
	},
	"WEB-SHARE-TARGET": {
		"href": "https://wicg.github.io/web-share-target/",
		"title": "Web Share Target API"
	},
	"WEBUSB": {
		"href": "https://wicg.github.io/webusb/",
		"title": "WebUSB API"
	}
}
